{
  "Alexander": "Maroseyka, 12 - Ivan Pavlyuchenko, Cobra. Black Blood - Pavlyuchenko, Atlantis - Yuri",
  "Anatoly": "Lenin in October - worker, Lenin in 1918 - sailor, Belorussky Railway Station - Nikolai Dubinsky",
  "Andrey": "And if it's love? - Peter, My younger brother - Yura Popov, Two Sundays - journalist",
  "Arnold": "Hercules in New York - Hercules, Stay hungry - Joy Santo, Conan the Barbarian - Conan",
  "Back to the future": {
    "actors": " Michael J. Fox - Marty McFly, Christopher Lloyd - Emmett Brown, Lea Thompson - Lorraine Baines, Crispin Glover - George McFly, Thomas F. Wilson - Biff Tannen, Claudia Wells - Jennifer Parker",
    "authors": "Robert Lee Zemeckis, Michael Robert Gale",
    "country": "USA",
    "data": "1985",
    "director": "Robert Lee Zemeckis",
    "producers": "Michael Robert Gale, Neil Canton",
    "studio": "Universal Pictures"
  },
  "Bean": "ABC Afterschool Specials - Seth, Family - Jake, Logan’s Run - Sandman",
  "Black": "Bob Roberts - Roger Davis, Airborne - Augie, Demolition Man - Westerland Scrap",
  "Christopher": "Back To The Future - Emmett Brown, One Flew Over the Cuckoo's Nest - Scott Howard, Light Of Day - Joey Resnick",
  "Claudia": "Back To The Future - Jennifer Parker, Rise and Shine - Patsy D'allisandro, Strike Force - Patty",
  "Crispin": "Back To The Future - George McFly, Happy Days - Roach, Hill Street Blues - cadet",
  "Cusack": "Class - Jennifer Parker, Sixteen Candles - Geek Girl #1, All Together Now - Linda Parker",
  "Derevyanko": "Two drivers were driving - Kolka Snegirev, Three sisters - the orderly, Mixer - Euphrosyne",
  "Diamond Hand": {
    "actors": " Yuri Nikulin - Semyon Gorbunkov, Andrey Mironov - Gennady Kozodoev, Anatoly Papanov - Lyolik",
    "authors": "Leonid Gaidai, Yakov Kostyukovsky, Maurice Slobodskoy",
    "country": "USSR",
    "data": "1969",
    "director": "Leonid Gaidai",
    "producers": "Arkady Ashkinazi",
    "studio": "Mosfilm"
  },
  "Fandera": "Adventures Electronics - schoolgirl, Ship - Yushka, Morning Highway - Natasha",
  "Fox": "Back To The Future - Marty McFly, Teen Wolf - Scott Howard, Light Of Day - Joey Resnick",
  "Glover": "Back To The Future - George McFly, Happy Days - Roach, Hill Street Blues - cadet",
  "Hamilton": "Night-Flowers - Waffle, Shirley - Gloria, Reunion - Ann Samurian",
  "Jack": "Bob Roberts - Roger Davis, Airborne - Augie, Demolition Man - Westerland Scrap",
  "Joan": "Class - Jennifer Parker, Sixteen Candles - Geek Girl #1, All Together Now - Linda Parker",
  "Lea": "Back To The Future - Lorraine Baines, All the Right Moves - Lisa Litzky, Jaws 3-D - Kelly Ann Bukowski",
  "Linda": "Night-Flowers - Waffle, Shirley - Gloria, Reunion - Ann Samurian",
  "Lloyd": "Back To The Future - Emmett Brown, One Flew Over the Cuckoo's Nest - Scott Howard, Light Of Day - Joey Resnick",
  "Michael": "ABC Afterschool Specials - Seth, Family - Jake, Logan’s Run - Sandman",
  "Mike": "Chuck & Buck - Buck O'Brien, Orange County - Mr. Burke, The School of Rock - Ned Schnibli",
  "Mironov": "And if it's love? - Peter, My younger brother - Yura Popov, Two Sundays - journalist",
  "Nikita": "Rope made of sand - Chest, Adjutants of Love - Peter Cherkasov, Trackways - Valery Fedorov",
  "Nikulin": "Unyielding - Vasily Klyachkin, Yasha Toporkov - Prosha, Dead souls - waiter",
  "Oksana": "Adventures Electronics - schoolgirl, Ship - Yushka, Morning Highway - Natasha",
  "Panfilov": "Rope made of sand - Chest, Adjutants of Love - Peter Cherkasov, Trackways - Valery Fedorov",
  "Papanov": "Lenin in October - worker, Lenin in 1918 - sailor, Belorussky Railway Station - Nikolai Dubinsky",
  "Pavel": "Two drivers were driving - Kolka Snegirev, Three sisters - the orderly, Mixer - Euphrosyne",
  "Samoylenko": "Maroseyka, 12 - Ivan Pavlyuchenko, Cobra. Black Blood - Pavlyuchenko, Atlantis - Yuri",
  "Schwarzenegger": "Hercules in New York - Hercules, Stay hungry - Joy Santo, Conan the Barbarian - Conan",
  "The School of Rock": {
    "actors": " Jack Black - Dewey Finn, Joan Cusack - Rosalie Mullins, Mike White - Ned Schnibli",
    "authors": "Mike White",
    "country": "USA",
    "data": "2003",
    "director": "Richard Linklater",
    "producers": "Scott Aversano, Steve Nicolaides, Scott Rudin",
    "studio": "Paramount Pictures"
  },
  "The Terminator": {
    "actors": " Michael Bean - Kyle Reese, Arnold Schwarzenegger - Terminato, Linda Hamilton - Sarah Connor",
    "authors": "James Cameron, Gail Ann Hurd",
    "country": "USA",
    "data": "1984",
    "director": "James Cameron",
    "producers": "Gail Ann Hurd",
    "studio": "Orion Pictures"
  },
  "Thomas": "Back To The Future - Biff Tannen, Knight Rider - Chip, April Fool‘s Day - Arch",
  "Thompson": "Back To The Future - Lorraine Baines, All the Right Moves - Lisa Litzky, Jaws 3-D - Kelly Ann Bukowski",
  "Vdovichenkov": "Boomer - Kostya, Time to collect stones - Captain Demin, Demons - Shatov",
  "Vladimir": "Boomer - Kostya, Time to collect stones - Captain Demin, Demons - Shatov",
  "Wells": "Back To The Future - Jennifer Parker, Rise and Shine - Patsy D'allisandro, Strike Force - Patty",
  "White": "Chuck & Buck - Buck O'Brien, Orange County - Mr. Burke, The School of Rock - Ned Schnibli",
  "Wilson": "Back To The Future - Biff Tannen, Knight Rider - Chip, April Fool‘s Day - Arch",
  "Yuri": "Unyielding - Vasily Klyachkin, Yasha Toporkov - Prosha, Dead souls - waiter",
  "salyut-7": {
    "actors": " Vladimir Vdovichenkov - Vladimir Fedorov, Pavel Derevyanko - Victor Alekhine, Alexander Samoylenko - Valery Shubin, Oksana Fandera - Svetlana Lazareva, Nikita Panfilov - Igor Zaitsev",
    "authors": "Natalia Merkulova, Alexey Samolyotov, Klim Shipenko, Alexey Chupov",
    "country": "Russia",
    "data": "2017",
    "director": "Klim Shipenko",
    "producers": "Anton Zlatopolsky, Sergey Selyanov, Bakur Bakuradze, Julia Mishkenene",
    "studio": "Vudu"
  }
}